{
    "type": "Feature",
    "stac_version": "1.0.0-beta.2",
    "id": "India_399883_label",
    "properties": {
        "country": "India",
        "chip_id": "399883",
        "label:description": "-1: NoData. 0: Not Water. 1: Water.",
        "label:type": "raster",
        "label:properties": null,
        "label:classes": [
            [
                0,
                1
            ]
        ],
        "label:tasks": [
            "classification"
        ],
        "datetime": "2016-08-12T00:00:00Z"
    },
    "geometry": {
        "type": "Polygon",
        "coordinates": [
            [
                [
                    93.36729737024659,
                    26.676370677213306
                ],
                [
                    93.36729737024659,
                    26.72236441976023
                ],
                [
                    93.32130362769966,
                    26.72236441976023
                ],
                [
                    93.32130362769966,
                    26.676370677213306
                ],
                [
                    93.36729737024659,
                    26.676370677213306
                ]
            ]
        ]
    },
    "links": [
        {
            "rel": "root",
            "href": "../../catalog.json",
            "type": "application/json"
        },
        {
            "rel": "collection",
            "href": "../collection.json",
            "type": "application/json"
        },
        {
            "rel": "parent",
            "href": "../collection.json",
            "type": "application/json"
        }
    ],
    "assets": {
        "LabelHand": {
            "href": "https://storage.googleapis.com/sen1floods11/v1.1/data/flood_events/HandLabeled/LabelHand/India_399883_LabelHand.tif",
            "type": "image/tiff; application=geotiff",
            "title": "GeoTiff"
        },
        "JRCWaterHand": {
            "href": "https://storage.googleapis.com/sen1floods11/v1.1/data/flood_events/HandLabeled/JRCWaterHand/India_399883_JRCWaterHand.tif",
            "type": "image/tiff; application=geotiff",
            "title": "GeoTiff"
        },
        "S1OtsuLabelHand": {
            "href": "https://storage.googleapis.com/sen1floods11/v1.1/data/flood_events/HandLabeled/S1OtsuLabelHand/India_399883_S1OtsuLabelHand.tif",
            "type": "image/tiff; application=geotiff",
            "title": "GeoTiff"
        }
    },
    "bbox": [
        93.32130362769966,
        26.676370677213306,
        93.36729737024659,
        26.72236441976023
    ],
    "stac_extensions": [
        "label"
    ],
    "collection": "sen1floods11_hand_labeled_label"
}