{
    "type": "Feature",
    "stac_version": "1.0.0-beta.2",
    "id": "India_833266_label",
    "properties": {
        "country": "India",
        "chip_id": "833266",
        "label:description": "-1: NoData. 0: Not Water. 1: Water.",
        "label:type": "raster",
        "label:properties": null,
        "label:classes": [
            [
                0,
                1
            ]
        ],
        "label:tasks": [
            "classification"
        ],
        "datetime": "2016-08-12T00:00:00Z"
    },
    "geometry": {
        "type": "Polygon",
        "coordinates": [
            [
                [
                    93.82723479571578,
                    26.630376934666387
                ],
                [
                    93.82723479571578,
                    26.67637067721331
                ],
                [
                    93.78124105316886,
                    26.67637067721331
                ],
                [
                    93.78124105316886,
                    26.630376934666387
                ],
                [
                    93.82723479571578,
                    26.630376934666387
                ]
            ]
        ]
    },
    "links": [
        {
            "rel": "root",
            "href": "../../catalog.json",
            "type": "application/json"
        },
        {
            "rel": "collection",
            "href": "../collection.json",
            "type": "application/json"
        },
        {
            "rel": "parent",
            "href": "../collection.json",
            "type": "application/json"
        }
    ],
    "assets": {
        "LabelHand": {
            "href": "https://storage.googleapis.com/sen1floods11/v1.1/data/flood_events/HandLabeled/LabelHand/India_833266_LabelHand.tif",
            "type": "image/tiff; application=geotiff",
            "title": "GeoTiff"
        },
        "JRCWaterHand": {
            "href": "https://storage.googleapis.com/sen1floods11/v1.1/data/flood_events/HandLabeled/JRCWaterHand/India_833266_JRCWaterHand.tif",
            "type": "image/tiff; application=geotiff",
            "title": "GeoTiff"
        },
        "S1OtsuLabelHand": {
            "href": "https://storage.googleapis.com/sen1floods11/v1.1/data/flood_events/HandLabeled/S1OtsuLabelHand/India_833266_S1OtsuLabelHand.tif",
            "type": "image/tiff; application=geotiff",
            "title": "GeoTiff"
        }
    },
    "bbox": [
        93.78124105316886,
        26.630376934666387,
        93.82723479571578,
        26.67637067721331
    ],
    "stac_extensions": [
        "label"
    ],
    "collection": "sen1floods11_hand_labeled_label"
}